pyseismic_lsr-0.4.3.dist-info/METADATA
pyseismic_lsr-0.4.3.dist-info/WHEEL
pyseismic_lsr-0.4.3.dist-info/license_files/LICENSE.md
seismic/__init__.py
seismic/seismic.cpython-310-x86_64-linux-gnu.so
pyseismic_lsr-0.4.3.dist-info/RECORD
