Metadata-Version: 2.1
Name: pyseismic-lsr
Version: 0.4.3
Classifier: Programming Language :: Rust
Classifier: Programming Language :: Python :: Implementation :: CPython
Classifier: Programming Language :: Python :: Implementation :: PyPy
Classifier: License :: OSI Approved :: MIT License
Requires-Dist: numpy
License-File: LICENSE.md
Summary: A high-performance data structure for fast retrieval over learned sparse representations
Keywords: search,indexing,sparse retrieval
Author-email: Sebastian Bruch <s.bruch@northeastern.edu>, Franco Maria Nardini <francomaria.nardini@isti.cnr.it>, Cosimo Rulli <cosimo.rulli@isti.cnr.it>, Rossano Venturini <rossano.venturini@unipi.it>, Leonardo Venuta <l.venuta@studenti.unipi.it>
License: MIT
Requires-Python: >=3.7
Project-URL: Source Code, https://github.com/TusKANNy/seismic
